mixy/__init__.py
mixy/cache_handler.py
mixy/cached_vars_handler.py
mixy/cli.py
mixy/constants.py
mixy/context.py
mixy/exceptions.py
mixy/git_manager.py
mixy/github_manager.py
mixy/logger_builder.py
mixy/merge_strategies.py
mixy/models/__init__.py
mixy/models/base.py
mixy/models/directory_dependency.py
mixy/models/file_dependency.py
mixy/models/git_dependency.py
mixy/models/log_level.py
mixy/models/mixy_dependency.py
mixy/models/mixy_file.py
mixy/models/project.py
mixy/models/template_var.py
mixy/preloaded_resolver.py
mixy/prompt_resolver.py
mixy/protocols/__init__.py
mixy/protocols/dependency.py
mixy/protocols/git_manager_protocol.py
mixy/protocols/merge_strategy.py
mixy/protocols/mergeable.py
mixy/protocols/renderable.py
mixy/protocols/repository_provider.py
mixy/protocols/resolver_protocol.py
mixy/protocols/var_protocol.py
mixy/protocols/vars_handler_protocol.py
mixy/settings/__init__.py
mixy/settings/cache_settings.py
mixy/settings/jinja_settings.py
mixy/settings/logging_settings.py
mixy/settings/project_settings.py
mixy/settings/settings.py
mixy/settings/sources.py
mixy/utils.py
mixy-1.10.1.dist-info/LICENSE
mixy-1.10.1.dist-info/METADATA
mixy-1.10.1.dist-info/WHEEL
mixy-1.10.1.dist-info/entry_points.txt
mixy-1.10.1.dist-info/RECORD
