Metadata-Version: 2.1
Name: mixy
Version: 1.10.1
Summary: 
Home-page: https://github.com/alexisbeaulieu97/Mixy
License: MIT
Author: Alexis Beaulieu
Author-email: alexisbeaulieu97@gmail.com
Requires-Python: >=3.11,<4.0
Classifier: License :: OSI Approved :: MIT License
Classifier: Programming Language :: Python :: 3
Classifier: Programming Language :: Python :: 3.11
Requires-Dist: gitpython (>=3.1.29,<4.0.0)
Requires-Dist: jinja2 (>=3.1.2,<4.0.0)
Requires-Dist: pydantic (>=1.10.2,<2.0.0)
Requires-Dist: pyyaml (>=6.0,<7.0)
Requires-Dist: requests (>=2.28.1,<3.0.0)
Requires-Dist: typer[all] (>=0.7.0,<0.8.0)
Project-URL: Repository, https://github.com/alexisbeaulieu97/Mixy
